{
 "displayFieldName": "USER_NIBRSClass",
 "fieldAliases": {
  "OBJECTID": "ObjectID",
  "USER_RMSOccurrenceDate": "USER_RMSOccurrenceDate",
  "USER_RMSOccurrenceHour": "USER_RMSOccurrenceHour",
  "USER_Incident": "USER_Incident",
  "USER_NIBRSClass": "USER_NIBRSClass",
  "USER_NIBRSDescription": "USER_NIBRSDescription",
  "USER_District": "USER_District",
  "USER_Beat": "USER_Beat",
  "USER_Premise": "USER_Premise",
  "USER_OffenseAddressMiddle": "USER_OffenseAddressMiddle",
  "USER_BlockRange": "USER_BlockRange",
  "USER_StreetName": "USER_StreetName",
  "USER_StreetType": "USER_StreetType",
  "USER_Suffix": "USER_Suffix",
  "USER_ZIPCode": "USER_ZIPCode",
  "USER_ORI": "USER_ORI",
  "DISTRICT_1": "DISTRICT",
  "SNBNAME": "SNBNAME",
  "OLC": "OLC"
 },
 "fields": [
  {
   "name": "OBJECTID",
   "type": "esriFieldTypeOID",
   "alias": "ObjectID"
  },
  {
   "name": "USER_RMSOccurrenceDate",
   "type": "esriFieldTypeDate",
   "alias": "USER_RMSOccurrenceDate",
   "length": 8
  },
  {
   "name": "USER_RMSOccurrenceHour",
   "type": "esriFieldTypeString",
   "alias": "USER_RMSOccurrenceHour",
   "length": 2
  },
  {
   "name": "USER_Incident",
   "type": "esriFieldTypeString",
   "alias": "USER_Incident",
   "length": 9
  },
  {
   "name": "USER_NIBRSClass",
   "type": "esriFieldTypeString",
   "alias": "USER_NIBRSClass",
   "length": 50
  },
  {
   "name": "USER_NIBRSDescription",
   "type": "esriFieldTypeString",
   "alias": "USER_NIBRSDescription",
   "length": 200
  },
  {
   "name": "USER_District",
   "type": "esriFieldTypeString",
   "alias": "USER_District",
   "length": 25
  },
  {
   "name": "USER_Beat",
   "type": "esriFieldTypeString",
   "alias": "USER_Beat",
   "length": 10
  },
  {
   "name": "USER_Premise",
   "type": "esriFieldTypeString",
   "alias": "USER_Premise",
   "length": 200
  },
  {
   "name": "USER_OffenseAddressMiddle",
   "type": "esriFieldTypeString",
   "alias": "USER_OffenseAddressMiddle",
   "length": 300
  },
  {
   "name": "USER_BlockRange",
   "type": "esriFieldTypeString",
   "alias": "USER_BlockRange",
   "length": 61
  },
  {
   "name": "USER_StreetName",
   "type": "esriFieldTypeString",
   "alias": "USER_StreetName",
   "length": 200
  },
  {
   "name": "USER_StreetType",
   "type": "esriFieldTypeString",
   "alias": "USER_StreetType",
   "length": 50
  },
  {
   "name": "USER_Suffix",
   "type": "esriFieldTypeString",
   "alias": "USER_Suffix",
   "length": 50
  },
  {
   "name": "USER_ZIPCode",
   "type": "esriFieldTypeString",
   "alias": "USER_ZIPCode",
   "length": 10
  },
  {
   "name": "USER_ORI",
   "type": "esriFieldTypeString",
   "alias": "USER_ORI",
   "length": 9
  },
  {
   "name": "DISTRICT_1",
   "type": "esriFieldTypeString",
   "alias": "DISTRICT",
   "length": 254
  },
  {
   "name": "SNBNAME",
   "type": "esriFieldTypeString",
   "alias": "SNBNAME",
   "length": 50
  },
  {
   "name": "OLC",
   "type": "esriFieldTypeString",
   "alias": "OLC",
   "length": 20
  }
 ],
 "features": [
  {
   "attributes": {
    "OBJECTID": 8714083,
    "USER_RMSOccurrenceDate": 1679616000000,
    "USER_RMSOccurrenceHour": "16",
    "USER_Incident": "042215323",
    "USER_NIBRSClass": "240",
    "USER_NIBRSDescription": "Motor vehicle theft",
    "USER_District": "04",
    "USER_Beat": "04F20",
    "USER_Premise": "Residence, Home (Includes Apartment)",
    "USER_OffenseAddressMiddle": "9549 KEMPWOOD",
    "USER_BlockRange": "9500-9599",
    "USER_StreetName": "KEMPWOOD",
    "USER_StreetType": "DR",
    "USER_Suffix": "",
    "USER_ZIPCode": "77080",
    "USER_ORI": "TXHPD0000",
    "DISTRICT_1": "A",
    "SNBNAME": "SPRING BRANCH NORTH",
    "OLC": "76X6RFCC+PP"
   }
  },
  {
   "attributes": {
    "OBJECTID": 8714475,
    "USER_RMSOccurrenceDate": 1679616000000,
    "USER_RMSOccurrenceHour": "23",
    "USER_Incident": "042005223",
    "USER_NIBRSClass": "290",
    "USER_NIBRSDescription": "Destruction, damage, vandalism",
    "USER_District": "07",
    "USER_Beat": "07C30",
    "USER_Premise": "Residence, Home (Includes Apartment)",
    "USER_OffenseAddressMiddle": "7349 CURRY",
    "USER_BlockRange": "7300-7399",
    "USER_StreetName": "CURRY",
    "USER_StreetType": "RD",
    "USER_Suffix": "",
    "USER_ZIPCode": "77093",
    "USER_ORI": "TXHPD0000",
    "DISTRICT_1": "H",
    "SNBNAME": "EASTEX - JENSEN AREA",
    "OLC": "76X6RMG6+8W"
   }
  },
  {
   "attributes": {
    "OBJECTID": 8714497,
    "USER_RMSOccurrenceDate": 1679616000000,
    "USER_RMSOccurrenceHour": "08",
    "USER_Incident": "041599023",
    "USER_NIBRSClass": "23C",
    "USER_NIBRSDescription": "Shoplifting",
    "USER_District": "03",
    "USER_Beat": "03B50",
    "USER_Premise": "Department, Discount Store",
    "USER_OffenseAddressMiddle": "4349 NORTH",
    "USER_BlockRange": "4300-4399",
    "USER_StreetName": "NORTH",
    "USER_StreetType": "FWY",
    "USER_Suffix": "",
    "USER_ZIPCode": "77022",
    "USER_ORI": "TXHPD0000",
    "DISTRICT_1": "H",
    "SNBNAME": "INDEPENDENCE HEIGHTS",
    "OLC": "76X6RJH9+2H"
   }
  },
  {
   "attributes": {
    "OBJECTID": 8714634,
    "USER_RMSOccurrenceDate": 1679616000000,
    "USER_RMSOccurrenceHour": "07",
    "USER_Incident": "042227423",
    "USER_NIBRSClass": "23F",
    "USER_NIBRSDescription": "Theft from motor vehicle",
    "USER_District": "03",
    "USER_Beat": "03B50",
    "USER_Premise": "Parking Lot, Garage",
    "USER_OffenseAddressMiddle": "4449 NORTH",
    "USER_BlockRange": "4400-4499",
    "USER_StreetName": "NORTH",
    "USER_StreetType": "FWY",
    "USER_Suffix": "",
    "USER_ZIPCode": "77022",
    "USER_ORI": "TXHPD0000",
    "DISTRICT_1": "H",
    "SNBNAME": "INDEPENDENCE HEIGHTS",
    "OLC": "76X6RJH9+W3"
   }
  },
  {
   "attributes": {
    "OBJECTID": 8714655,
    "USER_RMSOccurrenceDate": 1679616000000,
    "USER_RMSOccurrenceHour": "17",
    "USER_Incident": "041876923",
    "USER_NIBRSClass": "23C",
    "USER_NIBRSDescription": "Shoplifting",
    "USER_District": "03",
    "USER_Beat": "03B50",
    "USER_Premise": "Grocery, Supermarket",
    "USER_OffenseAddressMiddle": "4449 NORTH",
    "USER_BlockRange": "4400-4499",
    "USER_StreetName": "NORTH",
    "USER_StreetType": "FWY",
    "USER_Suffix": "",
    "USER_ZIPCode": "77022",
    "USER_ORI": "TXHPD0000",
    "DISTRICT_1": "H",
    "SNBNAME": "INDEPENDENCE HEIGHTS",
    "OLC": "76X6RJH9+W3"
   }
  },
  {
   "attributes": {
    "OBJECTID": 8714258,
    "USER_RMSOccurrenceDate": 1679616000000,
    "USER_RMSOccurrenceHour": "07",
    "USER_Incident": "041582123",
    "USER_NIBRSClass": "290",
    "USER_NIBRSDescription": "Destruction, damage, vandalism",
    "USER_District": "03",
    "USER_Beat": "03B10",
    "USER_Premise": "Commercial, Office Building",
    "USER_OffenseAddressMiddle": "12049 HEMPSTEAD",
    "USER_BlockRange": "12000-12099",
    "USER_StreetName": "HEMPSTEAD",
    "USER_StreetType": "RD",
    "USER_Suffix": "",
    "USER_ZIPCode": "77092",
    "USER_ORI": "TXHPD0000",
    "DISTRICT_1": "A",
    "SNBNAME": "LANGWOOD",
    "OLC": "76X6RGG4+3V"
   }
  },
  {
   "attributes": {
    "OBJECTID": 8714186,
    "USER_RMSOccurrenceDate": 1679616000000,
    "USER_RMSOccurrenceHour": "00",
    "USER_Incident": "043232023",
    "USER_NIBRSClass": "23H",
    "USER_NIBRSDescription": "All other larceny",
    "USER_District": "01",
    "USER_Beat": "01A20",
    "USER_Premise": "Residence, Home (Includes Apartment)",
    "USER_OffenseAddressMiddle": "3849 BRANDT",
    "USER_BlockRange": "3800-3899",
    "USER_StreetName": "BRANDT",
    "USER_StreetType": "ST",
    "USER_Suffix": "",
    "USER_ZIPCode": "77006",
    "USER_ORI": "TXHPD0000",
    "DISTRICT_1": "A",
    "SNBNAME": "ADDICKS PARK TEN",
    "OLC": "76X6R9GH+J2"
   }
  },
  {
   "attributes": {
    "OBJECTID": 8714195,
    "USER_RMSOccurrenceDate": 1679616000000,
    "USER_RMSOccurrenceHour": "07",
    "USER_Incident": "042017523",
    "USER_NIBRSClass": "220",
    "USER_NIBRSDescription": "Burglary, Breaking and Entering",
    "USER_District": "20",
    "USER_Beat": "20G10",
    "USER_Premise": "Residence, Home (Includes Apartment)",
    "USER_OffenseAddressMiddle": "2949 GESSNER",
    "USER_BlockRange": "2900-2999",
    "USER_StreetName": "GESSNER",
    "USER_StreetType": "RD",
    "USER_Suffix": "S",
    "USER_ZIPCode": "77063",
    "USER_ORI": "TXHPD0000",
    "DISTRICT_1": "A",
    "SNBNAME": "SPRING BRANCH NORTH",
    "OLC": "76X6RFG3+2V"
   }
  },
  {
   "attributes": {
    "OBJECTID": 8714265,
    "USER_RMSOccurrenceDate": 1679616000000,
    "USER_RMSOccurrenceHour": "00",
    "USER_Incident": "041494823",
    "USER_NIBRSClass": "290",
    "USER_NIBRSDescription": "Destruction, damage, vandalism",
    "USER_District": "03",
    "USER_Beat": "03B40",
    "USER_Premise": "Residence, Home (Includes Apartment)",
    "USER_OffenseAddressMiddle": "449 MARATHON OAK",
    "USER_BlockRange": "400-499",
    "USER_StreetName": "MARATHON OAK",
    "USER_StreetType": "PL",
    "USER_Suffix": "",
    "USER_ZIPCode": "",
    "USER_ORI": "TXHPD0000",
    "DISTRICT_1": "H",
    "SNBNAME": "INDEPENDENCE HEIGHTS",
    "OLC": "76X6RHFW+5R"
   }
  },
  {
   "attributes": {
    "OBJECTID": 8714836,
    "USER_RMSOccurrenceDate": 1679616000000,
    "USER_RMSOccurrenceHour": "17",
    "USER_Incident": "041859423",
    "USER_NIBRSClass": "220",
    "USER_NIBRSDescription": "Burglary, Breaking and Entering",
    "USER_District": "03",
    "USER_Beat": "03B50",
    "USER_Premise": "Residence, Home (Includes Apartment)",
    "USER_OffenseAddressMiddle": "7849 APPLETON",
    "USER_BlockRange": "7800-7899",
    "USER_StreetName": "APPLETON",
    "USER_StreetType": "ST",
    "USER_Suffix": "",
    "USER_ZIPCode": "77022",
    "USER_ORI": "TXHPD0000",
    "DISTRICT_1": "H",
    "SNBNAME": "NORTHSIDE/NORTHLINE",
    "OLC": "76X6RJMJ+5P"
   }
  },
  {
   "attributes": {
    "OBJECTID": 8714809,
    "USER_RMSOccurrenceDate": 1679616000000,
    "USER_RMSOccurrenceHour": "00",
    "USER_Incident": "041711623",
    "USER_NIBRSClass": "210",
    "USER_NIBRSDescription": "Extortion, Blackmail",
    "USER_District": "03",
    "USER_Beat": "03B10",
    "USER_Premise": "Residence, Home (Includes Apartment)",
    "USER_OffenseAddressMiddle": "5849 VIKING",
    "USER_BlockRange": "5800-5899",
    "USER_StreetName": "VIKING",
    "USER_StreetType": "DR",
    "USER_Suffix": "",
    "USER_ZIPCode": "77092",
    "USER_ORI": "TXHPD0000",
    "DISTRICT_1": "C",
    "SNBNAME": "CENTRAL NORTHWEST",
    "OLC": "76X6RGMF+R8"
   }
  },
  {
   "attributes": {
    "OBJECTID": 8714756,
    "USER_RMSOccurrenceDate": 1679616000000,
    "USER_RMSOccurrenceHour": "08",
    "USER_Incident": "045417623",
    "USER_NIBRSClass": "23H",
    "USER_NIBRSDescription": "All other larceny",
    "USER_District": "04",
    "USER_Beat": "04F20",
    "USER_Premise": "Residence, Home (Includes Apartment)",
    "USER_OffenseAddressMiddle": "4449 STANFORD",
    "USER_BlockRange": "4400-4499",
    "USER_StreetName": "STANFORD",
    "USER_StreetType": "CT",
    "USER_Suffix": "",
    "USER_ZIPCode": "77041",
    "USER_ORI": "TXHPD0000",
    "DISTRICT_1": "A",
    "SNBNAME": "WESTBRANCH",
    "OLC": "76X6RFM2+XX"
   }
  },
  {
   "attributes": {
    "OBJECTID": 8714897,
    "USER_RMSOccurrenceDate": 1679616000000,
    "USER_RMSOccurrenceHour": "16",
    "USER_Incident": "041838523",
    "USER_NIBRSClass": "23F",
    "USER_NIBRSDescription": "Theft from motor vehicle",
    "USER_District": "03",
    "USER_Beat": "03B10",
    "USER_Premise": "Residence, Home (Includes Apartment)",
    "USER_OffenseAddressMiddle": "4949 FEDERAL PLAZA",
    "USER_BlockRange": "4900-4999",
    "USER_StreetName": "FEDERAL PLAZA",
    "USER_StreetType": "DR",
    "USER_Suffix": "",
    "USER_ZIPCode": "77092",
    "USER_ORI": "TXHPD0000",
    "DISTRICT_1": "C",
    "SNBNAME": "FAIRBANKS / NORTHWEST CROSSING",
    "OLC": "76X6RGQ7+9V"
   }
  },
  {
   "attributes": {
    "OBJECTID": 8714969,
    "USER_RMSOccurrenceDate": 1679616000000,
    "USER_RMSOccurrenceHour": "08",
    "USER_Incident": "043779523",
    "USER_NIBRSClass": "23G",
    "USER_NIBRSDescription": "Theft of motor vehicle parts or accessory",
    "USER_District": "05",
    "USER_Beat": "05F30",
    "USER_Premise": "Parking Lot, Garage",
    "USER_OffenseAddressMiddle": "8249 PINEMONT",
    "USER_BlockRange": "8200-8299",
    "USER_StreetName": "PINEMONT",
    "USER_StreetType": "DR",
    "USER_Suffix": "",
    "USER_ZIPCode": "77040",
    "USER_ORI": "TXHPD0000",
    "DISTRICT_1": "A",
    "SNBNAME": "FAIRBANKS / NORTHWEST CROSSING",
    "OLC": "76X6RFRQ+F3"
   }
  },
  {
   "attributes": {
    "OBJECTID": 8714974,
    "USER_RMSOccurrenceDate": 1679616000000,
    "USER_RMSOccurrenceHour": "19",
    "USER_Incident": "041972123",
    "USER_NIBRSClass": "240",
    "USER_NIBRSDescription": "Motor vehicle theft",
    "USER_District": "03",
    "USER_Beat": "03B50",
    "USER_Premise": "Parking Lot, Garage",
    "USER_OffenseAddressMiddle": "4949 AIRLINE",
    "USER_BlockRange": "4900-4999",
    "USER_StreetName": "AIRLINE",
    "USER_StreetType": "DR",
    "USER_Suffix": "",
    "USER_ZIPCode": "77022",
    "USER_ORI": "TXHPD0000",
    "DISTRICT_1": "H",
    "SNBNAME": "NORTHSIDE/NORTHLINE",
    "OLC": "76X6RJQ8+56"
   }
  },
  {
   "attributes": {
    "OBJECTID": 8715070,
    "USER_RMSOccurrenceDate": 1679616000000,
    "USER_RMSOccurrenceHour": "12",
    "USER_Incident": "041746823",
    "USER_NIBRSClass": "290",
    "USER_NIBRSDescription": "Destruction, damage, vandalism",
    "USER_District": "07",
    "USER_Beat": "07C30",
    "USER_Premise": "Highway, Road, Street, Alley",
    "USER_OffenseAddressMiddle": "8649 JENSEN",
    "USER_BlockRange": "8600-8699",
    "USER_StreetName": "JENSEN",
    "USER_StreetType": "DR",
    "USER_Suffix": "",
    "USER_ZIPCode": "77093",
    "USER_ORI": "TXHPD0000",
    "DISTRICT_1": "H",
    "SNBNAME": "EASTEX - JENSEN AREA",
    "OLC": "76X6RMQ4+8V"
   }
  },
  {
   "attributes": {
    "OBJECTID": 8715087,
    "USER_RMSOccurrenceDate": 1679616000000,
    "USER_RMSOccurrenceHour": "15",
    "USER_Incident": "041817223",
    "USER_NIBRSClass": "23B",
    "USER_NIBRSDescription": "Purse-snatching",
    "USER_District": "03",
    "USER_Beat": "03B10",
    "USER_Premise": "Residence, Home (Includes Apartment)",
    "USER_OffenseAddressMiddle": "5149 CREEKMONT",
    "USER_BlockRange": "5100-5199",
    "USER_StreetName": "CREEKMONT",
    "USER_StreetType": "DR",
    "USER_Suffix": "",
    "USER_ZIPCode": "77091",
    "USER_ORI": "TXHPD0000",
    "DISTRICT_1": "C",
    "SNBNAME": "CENTRAL NORTHWEST",
    "OLC": "76X6RGRM+V2"
   }
  },
  {
   "attributes": {
    "OBJECTID": 8715204,
    "USER_RMSOccurrenceDate": 1679616000000,
    "USER_RMSOccurrenceHour": "20",
    "USER_Incident": "043138423",
    "USER_NIBRSClass": "23F",
    "USER_NIBRSDescription": "Theft from motor vehicle",
    "USER_District": "03",
    "USER_Beat": "03B10",
    "USER_Premise": "Parking Lot, Garage",
    "USER_OffenseAddressMiddle": "5549 BINGLE",
    "USER_BlockRange": "5500-5599",
    "USER_StreetName": "BINGLE",
    "USER_StreetType": "RD",
    "USER_Suffix": "",
    "USER_ZIPCode": "77092",
    "USER_ORI": "TXHPD0000",
    "DISTRICT_1": "A",
    "SNBNAME": "FAIRBANKS / NORTHWEST CROSSING",
    "OLC": "76X6RGW6+6C"
   }
  },
  {
   "attributes": {
    "OBJECTID": 8715724,
    "USER_RMSOccurrenceDate": 1679616000000,
    "USER_RMSOccurrenceHour": "22",
    "USER_Incident": "041981923",
    "USER_NIBRSClass": "120",
    "USER_NIBRSDescription": "Robbery",
    "USER_District": "06",
    "USER_Beat": "06B30",
    "USER_Premise": "Commercial, Office Building",
    "USER_OffenseAddressMiddle": "6049 ANTOINE",
    "USER_BlockRange": "6000-6099",
    "USER_StreetName": "ANTOINE",
    "USER_StreetType": "DR",
    "USER_Suffix": "",
    "USER_ZIPCode": "77091",
    "USER_ORI": "TXHPD0000",
    "DISTRICT_1": "A",
    "SNBNAME": "GREATER INWOOD",
    "OLC": "76X6VG3G+GM"
   }
  },
  {
   "attributes": {
    "OBJECTID": 8715770,
    "USER_RMSOccurrenceDate": 1679616000000,
    "USER_RMSOccurrenceHour": "17",
    "USER_Incident": "044246223",
    "USER_NIBRSClass": "290",
    "USER_NIBRSDescription": "Destruction, damage, vandalism",
    "USER_District": "06",
    "USER_Beat": "06B30",
    "USER_Premise": "Residence, Home (Includes Apartment)",
    "USER_OffenseAddressMiddle": "5549 DE SOTO",
    "USER_BlockRange": "5500-5599",
    "USER_StreetName": "DE SOTO",
    "USER_StreetType": "ST",
    "USER_Suffix": "",
    "USER_ZIPCode": "77091",
    "USER_ORI": "TXHPD0000",
    "DISTRICT_1": "A",
    "SNBNAME": "GREATER INWOOD",
    "OLC": "76X6VG3H+QX"
   }
  },
  {
   "attributes": {
    "OBJECTID": 8715800,
    "USER_RMSOccurrenceDate": 1679616000000,
    "USER_RMSOccurrenceHour": "14",
    "USER_Incident": "041765623",
    "USER_NIBRSClass": "23B",
    "USER_NIBRSDescription": "Purse-snatching",
    "USER_District": "05",
    "USER_Beat": "05F30",
    "USER_Premise": "Restaurant",
    "USER_OffenseAddressMiddle": "7949 TIDWELL",
    "USER_BlockRange": "7900-7999",
    "USER_StreetName": "TIDWELL",
    "USER_StreetType": "RD",
    "USER_Suffix": "W",
    "USER_ZIPCode": "77040",
    "USER_ORI": "TXHPD0000",
    "DISTRICT_1": "B",
    "SNBNAME": "EAST HOUSTON",
    "OLC": "76X6RPX9+V8"
   }
  },
  {
   "attributes": {
    "OBJECTID": 8715805,
    "USER_RMSOccurrenceDate": 1679616000000,
    "USER_RMSOccurrenceHour": "10",
    "USER_Incident": "041869323",
    "USER_NIBRSClass": "240",
    "USER_NIBRSDescription": "Motor vehicle theft",
    "USER_District": "18",
    "USER_Beat": "18F60",
    "USER_Premise": "Parking Lot, Garage",
    "USER_OffenseAddressMiddle": "6049 GESSNER",
    "USER_BlockRange": "6000-6099",
    "USER_StreetName": "GESSNER",
    "USER_StreetType": "RD",
    "USER_Suffix": "S",
    "USER_ZIPCode": "77036",
    "USER_ORI": "TXHPD0000",
    "DISTRICT_1": "A",
    "SNBNAME": "CARVERDALE",
    "OLC": "76X6VF43+QW"
   }
  },
  {
   "attributes": {
    "OBJECTID": 8715370,
    "USER_RMSOccurrenceDate": 1679616000000,
    "USER_RMSOccurrenceHour": "15",
    "USER_Incident": "041810323",
    "USER_NIBRSClass": "23F",
    "USER_NIBRSDescription": "Theft from motor vehicle",
    "USER_District": "06",
    "USER_Beat": "06B10",
    "USER_Premise": "Parking Lot, Garage",
    "USER_OffenseAddressMiddle": "9449 BAUMAN",
    "USER_BlockRange": "9400-9499",
    "USER_StreetName": "BAUMAN",
    "USER_StreetType": "RD",
    "USER_Suffix": "",
    "USER_ZIPCode": "77076",
    "USER_ORI": "TXHPD0000",
    "DISTRICT_1": "H",
    "SNBNAME": "NORTHSIDE/NORTHLINE",
    "OLC": "76X6RJWH+G7"
   }
  },
  {
   "attributes": {
    "OBJECTID": 8715318,
    "USER_RMSOccurrenceDate": 1679616000000,
    "USER_RMSOccurrenceHour": "15",
    "USER_Incident": "042145523",
    "USER_NIBRSClass": "240",
    "USER_NIBRSDescription": "Motor vehicle theft",
    "USER_District": "03",
    "USER_Beat": "03B10",
    "USER_Premise": "Parking Lot, Garage",
    "USER_OffenseAddressMiddle": "6049 SUNFOREST",
    "USER_BlockRange": "6000-6099",
    "USER_StreetName": "SUNFOREST",
    "USER_StreetType": "DR",
    "USER_Suffix": "W",
    "USER_ZIPCode": "77092",
    "USER_ORI": "TXHPD0000",
    "DISTRICT_1": "C",
    "SNBNAME": "GREATER INWOOD",
    "OLC": "76X6RGXC+8P"
   }
  },
  {
   "attributes": {
    "OBJECTID": 8715331,
    "USER_RMSOccurrenceDate": 1679616000000,
    "USER_RMSOccurrenceHour": "04",
    "USER_Incident": "041554323",
    "USER_NIBRSClass": "220",
    "USER_NIBRSDescription": "Burglary, Breaking and Entering",
    "USER_District": "08",
    "USER_Beat": "08C30",
    "USER_Premise": "Grocery, Supermarket",
    "USER_OffenseAddressMiddle": "8949 MESA",
    "USER_BlockRange": "8900-8999",
    "USER_StreetName": "MESA",
    "USER_StreetType": "DR",
    "USER_Suffix": "",
    "USER_ZIPCode": "77028",
    "USER_ORI": "TXHPD0000",
    "DISTRICT_1": "B",
    "SNBNAME": "EAST HOUSTON",
    "OLC": "76X6RPVQ+33"
   }
  },
  {
   "attributes": {
    "OBJECTID": 8715428,
    "USER_RMSOccurrenceDate": 1679616000000,
    "USER_RMSOccurrenceHour": "16",
    "USER_Incident": "041845623",
    "USER_NIBRSClass": "120",
    "USER_NIBRSDescription": "Robbery",
    "USER_District": "06",
    "USER_Beat": "06B10",
    "USER_Premise": "Restaurant",
    "USER_OffenseAddressMiddle": "5549 NORTH",
    "USER_BlockRange": "5500-5599",
    "USER_StreetName": "NORTH",
    "USER_StreetType": "FWY",
    "USER_Suffix": "",
    "USER_ZIPCode": "77076",
    "USER_ORI": "TXHPD0000",
    "DISTRICT_1": "H",
    "SNBNAME": "NORTHSIDE/NORTHLINE",
    "OLC": "76X6RJX4+24"
   }
  },
  {
   "attributes": {
    "OBJECTID": 8715502,
    "USER_RMSOccurrenceDate": 1679616000000,
    "USER_RMSOccurrenceHour": "03",
    "USER_Incident": "041539623",
    "USER_NIBRSClass": "220",
    "USER_NIBRSDescription": "Burglary, Breaking and Entering",
    "USER_District": "06",
    "USER_Beat": "06B10",
    "USER_Premise": "Residence, Home (Includes Apartment)",
    "USER_OffenseAddressMiddle": "5649 AIRLINE",
    "USER_BlockRange": "5600-5699",
    "USER_StreetName": "AIRLINE",
    "USER_StreetType": "DR",
    "USER_Suffix": "",
    "USER_ZIPCode": "77076",
    "USER_ORI": "TXHPD0000",
    "DISTRICT_1": "H",
    "SNBNAME": "NORTHSIDE/NORTHLINE",
    "OLC": "76X6RJX8+C5"
   }
  },
  {
   "attributes": {
    "OBJECTID": 8715459,
    "USER_RMSOccurrenceDate": 1679616000000,
    "USER_RMSOccurrenceHour": "05",
    "USER_Incident": "041560623",
    "USER_NIBRSClass": "220",
    "USER_NIBRSDescription": "Burglary, Breaking and Entering",
    "USER_District": "05",
    "USER_Beat": "05F30",
    "USER_Premise": "Restaurant",
    "USER_OffenseAddressMiddle": "5749 HOLLISTER",
    "USER_BlockRange": "5700-5799",
    "USER_StreetName": "HOLLISTER",
    "USER_StreetType": "ST",
    "USER_Suffix": "",
    "USER_ZIPCode": "77040",
    "USER_ORI": "TXHPD0000",
    "DISTRICT_1": "A",
    "SNBNAME": "FAIRBANKS / NORTHWEST CROSSING",
    "OLC": "76X6VF2W+83"
   }
  },
  {
   "attributes": {
    "OBJECTID": 8715460,
    "USER_RMSOccurrenceDate": 1679616000000,
    "USER_RMSOccurrenceHour": "14",
    "USER_Incident": "046991523",
    "USER_NIBRSClass": "23C",
    "USER_NIBRSDescription": "Shoplifting",
    "USER_District": "05",
    "USER_Beat": "05F30",
    "USER_Premise": "Department, Discount Store",
    "USER_OffenseAddressMiddle": "5749 HOLLISTER",
    "USER_BlockRange": "5700-5799",
    "USER_StreetName": "HOLLISTER",
    "USER_StreetType": "ST",
    "USER_Suffix": "",
    "USER_ZIPCode": "77040",
    "USER_ORI": "TXHPD0000",
    "DISTRICT_1": "A",
    "SNBNAME": "FAIRBANKS / NORTHWEST CROSSING",
    "OLC": "76X6VF2W+83"
   }
  },
  {
   "attributes": {
    "OBJECTID": 8715903,
    "USER_RMSOccurrenceDate": 1679616000000,
    "USER_RMSOccurrenceHour": "09",
    "USER_Incident": "041788723",
    "USER_NIBRSClass": "290",
    "USER_NIBRSDescription": "Destruction, damage, vandalism",
    "USER_District": "08",
    "USER_Beat": "08C50",
    "USER_Premise": "Commercial, Office Building",
    "USER_OffenseAddressMiddle": "9149 TIDWELL",
    "USER_BlockRange": "9100-9199",
    "USER_StreetName": "TIDWELL",
    "USER_StreetType": "RD",
    "USER_Suffix": "",
    "USER_ZIPCode": "",
    "USER_ORI": "TXHPD0000",
    "DISTRICT_1": "B",
    "SNBNAME": "EAST HOUSTON",
    "OLC": "76X6VP2V+33"
   }
  },
  {
   "attributes": {
    "OBJECTID": 8716092,
    "USER_RMSOccurrenceDate": 1679616000000,
    "USER_RMSOccurrenceHour": "02",
    "USER_Incident": "041570523",
    "USER_NIBRSClass": "200",
    "USER_NIBRSDescription": "Arson",
    "USER_District": "08",
    "USER_Beat": "08C50",
    "USER_Premise": "Residence, Home (Includes Apartment)",
    "USER_OffenseAddressMiddle": "9749 HADDICK",
    "USER_BlockRange": "9700-9799",
    "USER_StreetName": "HADDICK",
    "USER_StreetType": "",
    "USER_Suffix": "",
    "USER_ZIPCode": "77078",
    "USER_ORI": "TXHPD0000",
    "DISTRICT_1": "B",
    "SNBNAME": "EAST HOUSTON",
    "OLC": "76X6VP3H+Q4"
   }
  },
  {
   "attributes": {
    "OBJECTID": 8716073,
    "USER_RMSOccurrenceDate": 1679616000000,
    "USER_RMSOccurrenceHour": "00",
    "USER_Incident": "041687423",
    "USER_NIBRSClass": "26B",
    "USER_NIBRSDescription": "Credit card, ATM fraud",
    "USER_District": "08",
    "USER_Beat": "08C50",
    "USER_Premise": "Residence, Home (Includes Apartment)",
    "USER_OffenseAddressMiddle": "8049 CABOT",
    "USER_BlockRange": "8000-8099",
    "USER_StreetName": "CABOT",
    "USER_StreetType": "ST",
    "USER_Suffix": "",
    "USER_ZIPCode": "77078",
    "USER_ORI": "TXHPD0000",
    "DISTRICT_1": "B",
    "SNBNAME": "EAST HOUSTON",
    "OLC": "76X6VP3C+QG"
   }
  },
  {
   "attributes": {
    "OBJECTID": 8716029,
    "USER_RMSOccurrenceDate": 1679616000000,
    "USER_RMSOccurrenceHour": "00",
    "USER_Incident": "045300323",
    "USER_NIBRSClass": "23H",
    "USER_NIBRSDescription": "All other larceny",
    "USER_District": "06",
    "USER_Beat": "06B20",
    "USER_Premise": "Other, Unknown",
    "USER_OffenseAddressMiddle": "2149 WILBURFORCE",
    "USER_BlockRange": "2100-2199",
    "USER_StreetName": "WILBURFORCE",
    "USER_StreetType": "ST",
    "USER_Suffix": "",
    "USER_ZIPCode": "77091",
    "USER_ORI": "TXHPD0000",
    "DISTRICT_1": "B",
    "SNBNAME": "ACRES HOME",
    "OLC": "76X6VH55+43"
   }
  },
  {
   "attributes": {
    "OBJECTID": 8716152,
    "USER_RMSOccurrenceDate": 1679616000000,
    "USER_RMSOccurrenceHour": "21",
    "USER_Incident": "042157523",
    "USER_NIBRSClass": "220",
    "USER_NIBRSDescription": "Burglary, Breaking and Entering",
    "USER_District": "06",
    "USER_Beat": "06B10",
    "USER_Premise": "Residence, Home (Includes Apartment)",
    "USER_OffenseAddressMiddle": "6649 MUCKELROY",
    "USER_BlockRange": "6600-6699",
    "USER_StreetName": "MUCKELROY",
    "USER_StreetType": "",
    "USER_Suffix": "",
    "USER_ZIPCode": "77076",
    "USER_ORI": "TXHPD0000",
    "DISTRICT_1": "H",
    "SNBNAME": "NORTHSIDE/NORTHLINE",
    "OLC": "76X6VJ53+MF"
   }
  },
  {
   "attributes": {
    "OBJECTID": 8716283,
    "USER_RMSOccurrenceDate": 1679616000000,
    "USER_RMSOccurrenceHour": "20",
    "USER_Incident": "044852623",
    "USER_NIBRSClass": "23F",
    "USER_NIBRSDescription": "Theft from motor vehicle",
    "USER_District": "19",
    "USER_Beat": "19G10",
    "USER_Premise": "Parking Lot, Garage",
    "USER_OffenseAddressMiddle": "9449 SAM HOUSTON",
    "USER_BlockRange": "9400-9499",
    "USER_StreetName": "SAM HOUSTON",
    "USER_StreetType": "PKWY",
    "USER_Suffix": "W",
    "USER_ZIPCode": "77099",
    "USER_ORI": "TXHPD0000",
    "DISTRICT_1": "H",
    "SNBNAME": "NORTHSIDE/NORTHLINE",
    "OLC": "76X6VH6Q+7J"
   }
  },
  {
   "attributes": {
    "OBJECTID": 8716191,
    "USER_RMSOccurrenceDate": 1679616000000,
    "USER_RMSOccurrenceHour": "07",
    "USER_Incident": "041596623",
    "USER_NIBRSClass": "23G",
    "USER_NIBRSDescription": "Theft of motor vehicle parts or accessory",
    "USER_District": "22",
    "USER_Beat": "22B20",
    "USER_Premise": "Hotel, Motel, ETC",
    "USER_OffenseAddressMiddle": "749 SAM HOUSTON",
    "USER_BlockRange": "700-799",
    "USER_StreetName": "SAM HOUSTON",
    "USER_StreetType": "PKWY",
    "USER_Suffix": "N",
    "USER_ZIPCode": "77060",
    "USER_ORI": "TXHPD0000",
    "DISTRICT_1": "H",
    "SNBNAME": "NORTHSIDE/NORTHLINE",
    "OLC": "76X6VH6Q+72"
   }
  },
  {
   "attributes": {
    "OBJECTID": 8716209,
    "USER_RMSOccurrenceDate": 1679616000000,
    "USER_RMSOccurrenceHour": "03",
    "USER_Incident": "041677623",
    "USER_NIBRSClass": "23G",
    "USER_NIBRSDescription": "Theft of motor vehicle parts or accessory",
    "USER_District": "20",
    "USER_Beat": "20G20",
    "USER_Premise": "Parking Lot, Garage",
    "USER_OffenseAddressMiddle": "649 SAM HOUSTON",
    "USER_BlockRange": "600-699",
    "USER_StreetName": "SAM HOUSTON",
    "USER_StreetType": "PKWY",
    "USER_Suffix": "W",
    "USER_ZIPCode": "77042",
    "USER_ORI": "TXHPD0000",
    "DISTRICT_1": "H",
    "SNBNAME": "NORTHSIDE/NORTHLINE",
    "OLC": "76X6VH6Q+7J"
   }
  },
  {
   "attributes": {
    "OBJECTID": 8716227,
    "USER_RMSOccurrenceDate": 1679616000000,
    "USER_RMSOccurrenceHour": "15",
    "USER_Incident": "041793123",
    "USER_NIBRSClass": "23F",
    "USER_NIBRSDescription": "Theft from motor vehicle",
    "USER_District": "19",
    "USER_Beat": "19G10",
    "USER_Premise": "Parking Lot, Garage",
    "USER_OffenseAddressMiddle": "8149 SAM HOUSTON",
    "USER_BlockRange": "8100-8199",
    "USER_StreetName": "SAM HOUSTON",
    "USER_StreetType": "PKWY",
    "USER_Suffix": "W",
    "USER_ZIPCode": "77072",
    "USER_ORI": "TXHPD0000",
    "DISTRICT_1": "H",
    "SNBNAME": "NORTHSIDE/NORTHLINE",
    "OLC": "76X6VH6Q+7J"
   }
  },
  {
   "attributes": {
    "OBJECTID": 8716525,
    "USER_RMSOccurrenceDate": 1679616000000,
    "USER_RMSOccurrenceHour": "13",
    "USER_Incident": "041895023",
    "USER_NIBRSClass": "23G",
    "USER_NIBRSDescription": "Theft of motor vehicle parts or accessory",
    "USER_District": "06",
    "USER_Beat": "06B30",
    "USER_Premise": "Parking Lot, Garage",
    "USER_OffenseAddressMiddle": "7349 LANGFIELD",
    "USER_BlockRange": "7300-7399",
    "USER_StreetName": "LANGFIELD",
    "USER_StreetType": "RD",
    "USER_Suffix": "",
    "USER_ZIPCode": "77092",
    "USER_ORI": "TXHPD0000",
    "DISTRICT_1": "A",
    "SNBNAME": "FAIRBANKS / NORTHWEST CROSSING",
    "OLC": "76X6VF8X+4W"
   }
  },
  {
   "attributes": {
    "OBJECTID": 8716531,
    "USER_RMSOccurrenceDate": 1679616000000,
    "USER_RMSOccurrenceHour": "19",
    "USER_Incident": "041924323",
    "USER_NIBRSClass": "23G",
    "USER_NIBRSDescription": "Theft of motor vehicle parts or accessory",
    "USER_District": "06",
    "USER_Beat": "06B10",
    "USER_Premise": "Residence, Home (Includes Apartment)",
    "USER_OffenseAddressMiddle": "149 SPREADING OAK",
    "USER_BlockRange": "100-199",
    "USER_StreetName": "SPREADING OAK",
    "USER_StreetType": "DR",
    "USER_Suffix": "E",
    "USER_ZIPCode": "77076",
    "USER_ORI": "TXHPD0000",
    "DISTRICT_1": "H",
    "SNBNAME": "NORTHSIDE/NORTHLINE",
    "OLC": "76X6VJ73+4F"
   }
  },
  {
   "attributes": {
    "OBJECTID": 8716675,
    "USER_RMSOccurrenceDate": 1679616000000,
    "USER_RMSOccurrenceHour": "18",
    "USER_Incident": "041895323",
    "USER_NIBRSClass": "120",
    "USER_NIBRSDescription": "Robbery",
    "USER_District": "08",
    "USER_Beat": "08C60",
    "USER_Premise": "Convenience Store",
    "USER_OffenseAddressMiddle": "5649 LANGLEY",
    "USER_BlockRange": "5600-5699",
    "USER_StreetName": "LANGLEY",
    "USER_StreetType": "RD",
    "USER_Suffix": "",
    "USER_ZIPCode": "77016",
    "USER_ORI": "TXHPD0000",
    "DISTRICT_1": "B",
    "SNBNAME": "EAST LITTLE YORK / HOMESTEAD",
    "OLC": "76X6VM8R+QP"
   }
  },
  {
   "attributes": {
    "OBJECTID": 8716551,
    "USER_RMSOccurrenceDate": 1679616000000,
    "USER_RMSOccurrenceHour": "16",
    "USER_Incident": "041836323",
    "USER_NIBRSClass": "120",
    "USER_NIBRSDescription": "Robbery",
    "USER_District": "06",
    "USER_Beat": "06B10",
    "USER_Premise": "Restaurant",
    "USER_OffenseAddressMiddle": "7049 AIRLINE",
    "USER_BlockRange": "7000-7099",
    "USER_StreetName": "AIRLINE",
    "USER_StreetType": "DR",
    "USER_Suffix": "",
    "USER_ZIPCode": "77076",
    "USER_ORI": "TXHPD0000",
    "DISTRICT_1": "H",
    "SNBNAME": "NORTHSIDE/NORTHLINE",
    "OLC": "76X6VJ78+G3"
   }
  },
  {
   "attributes": {
    "OBJECTID": 8716603,
    "USER_RMSOccurrenceDate": 1679616000000,
    "USER_RMSOccurrenceHour": "09",
    "USER_Incident": "041660123",
    "USER_NIBRSClass": "23H",
    "USER_NIBRSDescription": "All other larceny",
    "USER_District": "06",
    "USER_Beat": "06B10",
    "USER_Premise": "Residence, Home (Includes Apartment)",
    "USER_OffenseAddressMiddle": "11349 BISCAYNE",
    "USER_BlockRange": "11300-11399",
    "USER_StreetName": "BISCAYNE",
    "USER_StreetType": "WAY",
    "USER_Suffix": "",
    "USER_ZIPCode": "77076",
    "USER_ORI": "TXHPD0000",
    "DISTRICT_1": "H",
    "SNBNAME": "NORTHSIDE/NORTHLINE",
    "OLC": "76X6VJ8C+9H"
   }
  },
  {
   "attributes": {
    "OBJECTID": 8716640,
    "USER_RMSOccurrenceDate": 1679616000000,
    "USER_RMSOccurrenceHour": "00",
    "USER_Incident": "041687923",
    "USER_NIBRSClass": "26B",
    "USER_NIBRSDescription": "Credit card, ATM fraud",
    "USER_District": "08",
    "USER_Beat": "08C60",
    "USER_Premise": "Residence, Home (Includes Apartment)",
    "USER_OffenseAddressMiddle": "10549 ENVOY",
    "USER_BlockRange": "10500-10599",
    "USER_StreetName": "ENVOY",
    "USER_StreetType": "ST",
    "USER_Suffix": "",
    "USER_ZIPCode": "77016",
    "USER_ORI": "TXHPD0000",
    "DISTRICT_1": "B",
    "SNBNAME": "EAST LITTLE YORK / HOMESTEAD",
    "OLC": "76X6VM8V+5X"
   }
  },
  {
   "attributes": {
    "OBJECTID": 8716632,
    "USER_RMSOccurrenceDate": 1679616000000,
    "USER_RMSOccurrenceHour": "10",
    "USER_Incident": "042186823",
    "USER_NIBRSClass": "240",
    "USER_NIBRSDescription": "Motor vehicle theft",
    "USER_District": "06",
    "USER_Beat": "06B10",
    "USER_Premise": "Bar, Nightclub",
    "USER_OffenseAddressMiddle": "7349 NORDLING",
    "USER_BlockRange": "7300-7399",
    "USER_StreetName": "NORDLING",
    "USER_StreetType": "RD",
    "USER_Suffix": "",
    "USER_ZIPCode": "77076",
    "USER_ORI": "TXHPD0000",
    "DISTRICT_1": "H",
    "SNBNAME": "NORTHSIDE/NORTHLINE",
    "OLC": "76X6VJ95+4G"
   }
  },
  {
   "attributes": {
    "OBJECTID": 8716804,
    "USER_RMSOccurrenceDate": 1679616000000,
    "USER_RMSOccurrenceHour": "12",
    "USER_Incident": "041721623",
    "USER_NIBRSClass": "26A",
    "USER_NIBRSDescription": "False pretenses, swindle",
    "USER_District": "06",
    "USER_Beat": "06B40",
    "USER_Premise": "Residence, Home (Includes Apartment)",
    "USER_OffenseAddressMiddle": "1849 LITTLE YORK",
    "USER_BlockRange": "1800-1899",
    "USER_StreetName": "LITTLE YORK",
    "USER_StreetType": "RD",
    "USER_Suffix": "W",
    "USER_ZIPCode": "77088",
    "USER_ORI": "TXHPD0000",
    "DISTRICT_1": "H",
    "SNBNAME": "EASTEX - JENSEN AREA",
    "OLC": "76X6VJCV+96"
   }
  },
  {
   "attributes": {
    "OBJECTID": 8716741,
    "USER_RMSOccurrenceDate": 1679616000000,
    "USER_RMSOccurrenceHour": "17",
    "USER_Incident": "041877723",
    "USER_NIBRSClass": "23F",
    "USER_NIBRSDescription": "Theft from motor vehicle",
    "USER_District": "06",
    "USER_Beat": "06B10",
    "USER_Premise": "Parking Lot, Garage",
    "USER_OffenseAddressMiddle": "449 LITTLE YORK",
    "USER_BlockRange": "400-499",
    "USER_StreetName": "LITTLE YORK",
    "USER_StreetType": "RD",
    "USER_Suffix": "E",
    "USER_ZIPCode": "77037",
    "USER_ORI": "TXHPD0000",
    "DISTRICT_1": "H",
    "SNBNAME": "NORTHSIDE/NORTHLINE",
    "OLC": "76X6VJCF+3F"
   }
  },
  {
   "attributes": {
    "OBJECTID": 8716763,
    "USER_RMSOccurrenceDate": 1679616000000,
    "USER_RMSOccurrenceHour": "19",
    "USER_Incident": "042139523",
    "USER_NIBRSClass": "23F",
    "USER_NIBRSDescription": "Theft from motor vehicle",
    "USER_District": "06",
    "USER_Beat": "06B10",
    "USER_Premise": "Parking Lot, Garage",
    "USER_OffenseAddressMiddle": "649 LITTLE YORK",
    "USER_BlockRange": "600-699",
    "USER_StreetName": "LITTLE YORK",
    "USER_StreetType": "RD",
    "USER_Suffix": "E",
    "USER_ZIPCode": "77037",
    "USER_ORI": "TXHPD0000",
    "DISTRICT_1": "H",
    "SNBNAME": "NORTHSIDE/NORTHLINE",
    "OLC": "76X6VJCG+4X"
   }
  },
  {
   "attributes": {
    "OBJECTID": 8716901,
    "USER_RMSOccurrenceDate": 1679616000000,
    "USER_RMSOccurrenceHour": "11",
    "USER_Incident": "041698523",
    "USER_NIBRSClass": "290",
    "USER_NIBRSDescription": "Destruction, damage, vandalism",
    "USER_District": "08",
    "USER_Beat": "08C60",
    "USER_Premise": "Residence, Home (Includes Apartment)",
    "USER_OffenseAddressMiddle": "7449 IDA WELLS FOREST",
    "USER_BlockRange": "7400-7499",
    "USER_StreetName": "IDA WELLS FOREST",
    "USER_StreetType": "DR",
    "USER_Suffix": "",
    "USER_ZIPCode": "77016",
    "USER_ORI": "TXHPD0000",
    "DISTRICT_1": "B",
    "SNBNAME": "EAST LITTLE YORK / HOMESTEAD",
    "OLC": "76X6VPC4+CC"
   }
  },
  {
   "attributes": {
    "OBJECTID": 8716902,
    "USER_RMSOccurrenceDate": 1679616000000,
    "USER_RMSOccurrenceHour": "23",
    "USER_Incident": "042786323",
    "USER_NIBRSClass": "23F",
    "USER_NIBRSDescription": "Theft from motor vehicle",
    "USER_District": "06",
    "USER_Beat": "06B30",
    "USER_Premise": "Parking Lot, Garage",
    "USER_OffenseAddressMiddle": "5749 LITTLE YORK",
    "USER_BlockRange": "5700-5799",
    "USER_StreetName": "LITTLE YORK",
    "USER_StreetType": "RD",
    "USER_Suffix": "W",
    "USER_ZIPCode": "77088",
    "USER_ORI": "TXHPD0000",
    "DISTRICT_1": "B",
    "SNBNAME": "EAST LITTLE YORK / HOMESTEAD",
    "OLC": "76X6VMCV+GJ"
   }
  },
  {
   "attributes": {
    "OBJECTID": 8716947,
    "USER_RMSOccurrenceDate": 1679616000000,
    "USER_RMSOccurrenceHour": "09",
    "USER_Incident": "041630423",
    "USER_NIBRSClass": "220",
    "USER_NIBRSDescription": "Burglary, Breaking and Entering",
    "USER_District": "06",
    "USER_Beat": "06B30",
    "USER_Premise": "Residence, Home (Includes Apartment)",
    "USER_OffenseAddressMiddle": "7749 CHALLIE",
    "USER_BlockRange": "7700-7799",
    "USER_StreetName": "CHALLIE",
    "USER_StreetType": "LN",
    "USER_Suffix": "",
    "USER_ZIPCode": "77088",
    "USER_ORI": "TXHPD0000",
    "DISTRICT_1": "A",
    "SNBNAME": "GREATER INWOOD",
    "OLC": "76X6VGHF+F6"
   }
  },
  {
   "attributes": {
    "OBJECTID": 8716948,
    "USER_RMSOccurrenceDate": 1679616000000,
    "USER_RMSOccurrenceHour": "12",
    "USER_Incident": "057174123",
    "USER_NIBRSClass": "240",
    "USER_NIBRSDescription": "Motor vehicle theft",
    "USER_District": "06",
    "USER_Beat": "06B40",
    "USER_Premise": "Residence, Home (Includes Apartment)",
    "USER_OffenseAddressMiddle": "1649 FERGUSON",
    "USER_BlockRange": "1600-1699",
    "USER_StreetName": "FERGUSON",
    "USER_StreetType": "WAY",
    "USER_Suffix": "",
    "USER_ZIPCode": "77088",
    "USER_ORI": "TXHPD0000",
    "DISTRICT_1": "B",
    "SNBNAME": "ACRES HOME",
    "OLC": "76X6VHH7+54"
   }
  },
  {
   "attributes": {
    "OBJECTID": 8717007,
    "USER_RMSOccurrenceDate": 1679616000000,
    "USER_RMSOccurrenceHour": "02",
    "USER_Incident": "041824523",
    "USER_NIBRSClass": "290",
    "USER_NIBRSDescription": "Destruction, damage, vandalism",
    "USER_District": "06",
    "USER_Beat": "06B30",
    "USER_Premise": "Residence, Home (Includes Apartment)",
    "USER_OffenseAddressMiddle": "5349 GULF BANK",
    "USER_BlockRange": "5300-5399",
    "USER_StreetName": "GULF BANK",
    "USER_StreetType": "RD",
    "USER_Suffix": "W",
    "USER_ZIPCode": "77088",
    "USER_ORI": "TXHPD0000",
    "DISTRICT_1": "A",
    "SNBNAME": "GREATER INWOOD",
    "OLC": "76X6VGMM+7H"
   }
  },
  {
   "attributes": {
    "OBJECTID": 8717342,
    "USER_RMSOccurrenceDate": 1679616000000,
    "USER_RMSOccurrenceHour": "06",
    "USER_Incident": "041624323",
    "USER_NIBRSClass": "220",
    "USER_NIBRSDescription": "Burglary, Breaking and Entering",
    "USER_District": "22",
    "USER_Beat": "22B30",
    "USER_Premise": "Grocery, Supermarket",
    "USER_OffenseAddressMiddle": "149 FALLBROOK",
    "USER_BlockRange": "100-199",
    "USER_StreetName": "FALLBROOK",
    "USER_StreetType": "DR",
    "USER_Suffix": "",
    "USER_ZIPCode": "77038",
    "USER_ORI": "TXHPD0000",
    "DISTRICT_1": "B",
    "SNBNAME": "GREATER GREENSPOINT",
    "OLC": "76X6WHJP+MF"
   }
  },
  {
   "attributes": {
    "OBJECTID": 8717354,
    "USER_RMSOccurrenceDate": 1679616000000,
    "USER_RMSOccurrenceHour": "05",
    "USER_Incident": "041666623",
    "USER_NIBRSClass": "220",
    "USER_NIBRSDescription": "Burglary, Breaking and Entering",
    "USER_District": "22",
    "USER_Beat": "22B30",
    "USER_Premise": "Residence, Home (Includes Apartment)",
    "USER_OffenseAddressMiddle": "149 ALDINE BENDER",
    "USER_BlockRange": "100-199",
    "USER_StreetName": "ALDINE BENDER",
    "USER_StreetType": "RD",
    "USER_Suffix": "",
    "USER_ZIPCode": "77060",
    "USER_ORI": "TXHPD0000",
    "DISTRICT_1": "B",
    "SNBNAME": "GREATER GREENSPOINT",
    "OLC": "76X6WHJW+PG"
   }
  },
  {
   "attributes": {
    "OBJECTID": 8717509,
    "USER_RMSOccurrenceDate": 1679616000000,
    "USER_RMSOccurrenceHour": "16",
    "USER_Incident": "041829023",
    "USER_NIBRSClass": "290",
    "USER_NIBRSDescription": "Destruction, damage, vandalism",
    "USER_District": "17",
    "USER_Beat": "17E40",
    "USER_Premise": "Highway, Road, Street, Alley",
    "USER_OffenseAddressMiddle": "11949 GESSNER",
    "USER_BlockRange": "11900-11999",
    "USER_StreetName": "GESSNER",
    "USER_StreetType": "RD",
    "USER_Suffix": "S",
    "USER_ZIPCode": "77071",
    "USER_ORI": "TXHPD0000",
    "DISTRICT_1": "A",
    "SNBNAME": "WILLOWBROOK",
    "OLC": "76X6WFW3+H7"
   }
  },
  {
   "attributes": {
    "OBJECTID": 8717512,
    "USER_RMSOccurrenceDate": 1679616000000,
    "USER_RMSOccurrenceHour": "05",
    "USER_Incident": "041694023",
    "USER_NIBRSClass": "23G",
    "USER_NIBRSDescription": "Theft of motor vehicle parts or accessory",
    "USER_District": "22",
    "USER_Beat": "22B20",
    "USER_Premise": "Hotel, Motel, ETC",
    "USER_OffenseAddressMiddle": "349 UNITED LEUVA",
    "USER_BlockRange": "300-399",
    "USER_StreetName": "UNITED LEUVA",
    "USER_StreetType": "CIR",
    "USER_Suffix": "",
    "USER_ZIPCode": "",
    "USER_ORI": "TXHPD0000",
    "DISTRICT_1": "B",
    "SNBNAME": "GREATER GREENSPOINT",
    "OLC": "76X6WJV2+38"
   }
  },
  {
   "attributes": {
    "OBJECTID": 8717470,
    "USER_RMSOccurrenceDate": 1679616000000,
    "USER_RMSOccurrenceHour": "16",
    "USER_Incident": "042181123",
    "USER_NIBRSClass": "23G",
    "USER_NIBRSDescription": "Theft of motor vehicle parts or accessory",
    "USER_District": "22",
    "USER_Beat": "22B30",
    "USER_Premise": "Commercial, Office Building",
    "USER_OffenseAddressMiddle": "11049 GREENS CROSSING",
    "USER_BlockRange": "11000-11099",
    "USER_StreetName": "GREENS CROSSING",
    "USER_StreetType": "BLVD",
    "USER_Suffix": "",
    "USER_ZIPCode": "77067",
    "USER_ORI": "TXHPD0000",
    "DISTRICT_1": "B",
    "SNBNAME": "GREATER GREENSPOINT",
    "OLC": "76X6WHRF+8X"
   }
  },
  {
   "attributes": {
    "OBJECTID": 8717476,
    "USER_RMSOccurrenceDate": 1679616000000,
    "USER_RMSOccurrenceHour": "21",
    "USER_Incident": "042142023",
    "USER_NIBRSClass": "23G",
    "USER_NIBRSDescription": "Theft of motor vehicle parts or accessory",
    "USER_District": "22",
    "USER_Beat": "22B40",
    "USER_Premise": "Parking Lot, Garage",
    "USER_OffenseAddressMiddle": "15149 VICKERY",
    "USER_BlockRange": "15100-15199",
    "USER_StreetName": "VICKERY",
    "USER_StreetType": "DR",
    "USER_Suffix": "",
    "USER_ZIPCode": "77032",
    "USER_ORI": "TXHPD0000",
    "DISTRICT_1": "B",
    "SNBNAME": "IAH / AIRPORT AREA",
    "OLC": "76X6WMQM+8P"
   }
  },
  {
   "attributes": {
    "OBJECTID": 8717477,
    "USER_RMSOccurrenceDate": 1679616000000,
    "USER_RMSOccurrenceHour": "21",
    "USER_Incident": "042142023",
    "USER_NIBRSClass": "290",
    "USER_NIBRSDescription": "Destruction, damage, vandalism",
    "USER_District": "22",
    "USER_Beat": "22B40",
    "USER_Premise": "Parking Lot, Garage",
    "USER_OffenseAddressMiddle": "15149 VICKERY",
    "USER_BlockRange": "15100-15199",
    "USER_StreetName": "VICKERY",
    "USER_StreetType": "DR",
    "USER_Suffix": "",
    "USER_ZIPCode": "77032",
    "USER_ORI": "TXHPD0000",
    "DISTRICT_1": "B",
    "SNBNAME": "IAH / AIRPORT AREA",
    "OLC": "76X6WMQM+8P"
   }
  },
  {
   "attributes": {
    "OBJECTID": 8717084,
    "USER_RMSOccurrenceDate": 1679616000000,
    "USER_RMSOccurrenceHour": "01",
    "USER_Incident": "041520523",
    "USER_NIBRSClass": "290",
    "USER_NIBRSDescription": "Destruction, damage, vandalism",
    "USER_District": "06",
    "USER_Beat": "06B10",
    "USER_Premise": "Residence, Home (Includes Apartment)",
    "USER_OffenseAddressMiddle": "1249 HARTWICK",
    "USER_BlockRange": "1200-1299",
    "USER_StreetName": "HARTWICK",
    "USER_StreetType": "RD",
    "USER_Suffix": "",
    "USER_ZIPCode": "77037",
    "USER_ORI": "TXHPD0000",
    "DISTRICT_1": "H",
    "SNBNAME": "NORTHSIDE/NORTHLINE",
    "OLC": "76X6VJMH+WG"
   }
  },
  {
   "attributes": {
    "OBJECTID": 8717143,
    "USER_RMSOccurrenceDate": 1679616000000,
    "USER_RMSOccurrenceHour": "21",
    "USER_Incident": "041973123",
    "USER_NIBRSClass": "23F",
    "USER_NIBRSDescription": "Theft from motor vehicle",
    "USER_District": "06",
    "USER_Beat": "06B40",
    "USER_Premise": "Other, Unknown",
    "USER_OffenseAddressMiddle": "1449 GULF BANK",
    "USER_BlockRange": "1400-1499",
    "USER_StreetName": "GULF BANK",
    "USER_StreetType": "RD",
    "USER_Suffix": "W",
    "USER_ZIPCode": "77088",
    "USER_ORI": "TXHPD0000",
    "DISTRICT_1": "",
    "SNBNAME": "",
    "OLC": "76X6VJRJ+7V"
   }
  },
  {
   "attributes": {
    "OBJECTID": 8717144,
    "USER_RMSOccurrenceDate": 1679616000000,
    "USER_RMSOccurrenceHour": "21",
    "USER_Incident": "041973123",
    "USER_NIBRSClass": "290",
    "USER_NIBRSDescription": "Destruction, damage, vandalism",
    "USER_District": "06",
    "USER_Beat": "06B40",
    "USER_Premise": "Other, Unknown",
    "USER_OffenseAddressMiddle": "1449 GULF BANK",
    "USER_BlockRange": "1400-1499",
    "USER_StreetName": "GULF BANK",
    "USER_StreetType": "RD",
    "USER_Suffix": "W",
    "USER_ZIPCode": "77088",
    "USER_ORI": "TXHPD0000",
    "DISTRICT_1": "",
    "SNBNAME": "",
    "OLC": "76X6VJRJ+7V"
   }
  },
  {
   "attributes": {
    "OBJECTID": 8717110,
    "USER_RMSOccurrenceDate": 1679616000000,
    "USER_RMSOccurrenceHour": "04",
    "USER_Incident": "041611523",
    "USER_NIBRSClass": "240",
    "USER_NIBRSDescription": "Motor vehicle theft",
    "USER_District": "06",
    "USER_Beat": "06B40",
    "USER_Premise": "Parking Lot, Garage",
    "USER_OffenseAddressMiddle": "8949 NORTH",
    "USER_BlockRange": "8900-8999",
    "USER_StreetName": "NORTH",
    "USER_StreetType": "FWY",
    "USER_Suffix": "",
    "USER_ZIPCode": "77037",
    "USER_ORI": "TXHPD0000",
    "DISTRICT_1": "B",
    "SNBNAME": "HIDDEN VALLEY",
    "OLC": "76X6VHQP+8X"
   }
  },
  {
   "attributes": {
    "OBJECTID": 8717210,
    "USER_RMSOccurrenceDate": 1679616000000,
    "USER_RMSOccurrenceHour": "02",
    "USER_Incident": "041536623",
    "USER_NIBRSClass": "290",
    "USER_NIBRSDescription": "Destruction, damage, vandalism",
    "USER_District": "06",
    "USER_Beat": "06B40",
    "USER_Premise": "Department, Discount Store",
    "USER_OffenseAddressMiddle": "149 WEST",
    "USER_BlockRange": "100-199",
    "USER_StreetName": "WEST",
    "USER_StreetType": "RD",
    "USER_Suffix": "",
    "USER_ZIPCode": "77037",
    "USER_ORI": "TXHPD0000",
    "DISTRICT_1": "",
    "SNBNAME": "",
    "OLC": "76X6WH8R+3R"
   }
  },
  {
   "attributes": {
    "OBJECTID": 8717806,
    "USER_RMSOccurrenceDate": 1679616000000,
    "USER_RMSOccurrenceHour": "08",
    "USER_Incident": "041631023",
    "USER_NIBRSClass": "23H",
    "USER_NIBRSDescription": "All other larceny",
    "USER_District": "22",
    "USER_Beat": "22B20",
    "USER_Premise": "Government, Public Building",
    "USER_OffenseAddressMiddle": "249 MEADOWFERN",
    "USER_BlockRange": "200-299",
    "USER_StreetName": "MEADOWFERN",
    "USER_StreetType": "DR",
    "USER_Suffix": "",
    "USER_ZIPCode": "77067",
    "USER_ORI": "TXHPD0000",
    "DISTRICT_1": "B",
    "SNBNAME": "GREATER GREENSPOINT",
    "OLC": "76X6XH3H+RX"
   }
  },
  {
   "attributes": {
    "OBJECTID": 8717939,
    "USER_RMSOccurrenceDate": 1679616000000,
    "USER_RMSOccurrenceHour": "10",
    "USER_Incident": "041820323",
    "USER_NIBRSClass": "26F",
    "USER_NIBRSDescription": "Identify theft",
    "USER_District": "22",
    "USER_Beat": "22B40",
    "USER_Premise": "Residence, Home (Includes Apartment)",
    "USER_OffenseAddressMiddle": "5949 MARWOOD",
    "USER_BlockRange": "5900-5999",
    "USER_StreetName": "MARWOOD",
    "USER_StreetType": "DR",
    "USER_Suffix": "",
    "USER_ZIPCode": "77396",
    "USER_ORI": "TXHPD0000",
    "DISTRICT_1": "B",
    "SNBNAME": "IAH / AIRPORT AREA",
    "OLC": "76X6XM7X+G2"
   }
  },
  {
   "attributes": {
    "OBJECTID": 8717680,
    "USER_RMSOccurrenceDate": 1679616000000,
    "USER_RMSOccurrenceHour": "17",
    "USER_Incident": "044165923",
    "USER_NIBRSClass": "23G",
    "USER_NIBRSDescription": "Theft of motor vehicle parts or accessory",
    "USER_District": "22",
    "USER_Beat": "22B40",
    "USER_Premise": "Industrial Site",
    "USER_OffenseAddressMiddle": "5649 SHIRLEY",
    "USER_BlockRange": "5600-5699",
    "USER_StreetName": "SHIRLEY",
    "USER_StreetType": "LN",
    "USER_Suffix": "",
    "USER_ZIPCode": "77032",
    "USER_ORI": "TXHPD0000",
    "DISTRICT_1": "B",
    "SNBNAME": "IAH / AIRPORT AREA",
    "OLC": "76X6WMWR+5M"
   }
  },
  {
   "attributes": {
    "OBJECTID": 8717668,
    "USER_RMSOccurrenceDate": 1679616000000,
    "USER_RMSOccurrenceHour": "13",
    "USER_Incident": "041749223",
    "USER_NIBRSClass": "240",
    "USER_NIBRSDescription": "Motor vehicle theft",
    "USER_District": "22",
    "USER_Beat": "22B20",
    "USER_Premise": "Residence, Home (Includes Apartment)",
    "USER_OffenseAddressMiddle": "17149 IMPERIAL VALLEY",
    "USER_BlockRange": "17100-17199",
    "USER_StreetName": "IMPERIAL VALLEY",
    "USER_StreetType": "DR",
    "USER_Suffix": "",
    "USER_ZIPCode": "77060",
    "USER_ORI": "TXHPD0000",
    "DISTRICT_1": "B",
    "SNBNAME": "GREATER GREENSPOINT",
    "OLC": "76X6WJX3+22"
   }
  },
  {
   "attributes": {
    "OBJECTID": 8717706,
    "USER_RMSOccurrenceDate": 1679616000000,
    "USER_RMSOccurrenceHour": "17",
    "USER_Incident": "042637223",
    "USER_NIBRSClass": "23G",
    "USER_NIBRSDescription": "Theft of motor vehicle parts or accessory",
    "USER_District": "22",
    "USER_Beat": "22B20",
    "USER_Premise": "Hotel, Motel, ETC",
    "USER_OffenseAddressMiddle": "12449 GREENSPOINT",
    "USER_BlockRange": "12400-12499",
    "USER_StreetName": "GREENSPOINT",
    "USER_StreetType": "DR",
    "USER_Suffix": "",
    "USER_ZIPCode": "77060",
    "USER_ORI": "TXHPD0000",
    "DISTRICT_1": "B",
    "SNBNAME": "GREATER GREENSPOINT",
    "OLC": "76X6WHXQ+PM"
   }
  },
  {
   "attributes": {
    "OBJECTID": 8717739,
    "USER_RMSOccurrenceDate": 1679616000000,
    "USER_RMSOccurrenceHour": "00",
    "USER_Incident": "041502923",
    "USER_NIBRSClass": "120",
    "USER_NIBRSDescription": "Robbery",
    "USER_District": "22",
    "USER_Beat": "22B20",
    "USER_Premise": "Park/Playground",
    "USER_OffenseAddressMiddle": "17449 IMPERIAL VALLEY",
    "USER_BlockRange": "17400-17499",
    "USER_StreetName": "IMPERIAL VALLEY",
    "USER_StreetType": "DR",
    "USER_Suffix": "",
    "USER_ZIPCode": "77060",
    "USER_ORI": "TXHPD0000",
    "DISTRICT_1": "B",
    "SNBNAME": "GREATER GREENSPOINT",
    "OLC": "76X6XJ22+46"
   }
  },
  {
   "attributes": {
    "OBJECTID": 8717567,
    "USER_RMSOccurrenceDate": 1679616000000,
    "USER_RMSOccurrenceHour": "17",
    "USER_Incident": "042144523",
    "USER_NIBRSClass": "23F",
    "USER_NIBRSDescription": "Theft from motor vehicle",
    "USER_District": "22",
    "USER_Beat": "22B20",
    "USER_Premise": "Parking Lot, Garage",
    "USER_OffenseAddressMiddle": "1449 GEARS",
    "USER_BlockRange": "1400-1499",
    "USER_StreetName": "GEARS",
    "USER_StreetType": "RD",
    "USER_Suffix": "",
    "USER_ZIPCode": "77067",
    "USER_ORI": "TXHPD0000",
    "DISTRICT_1": "",
    "SNBNAME": "",
    "OLC": "76X6WHW4+9J"
   }
  },
  {
   "attributes": {
    "OBJECTID": 8717590,
    "USER_RMSOccurrenceDate": 1679616000000,
    "USER_RMSOccurrenceHour": "18",
    "USER_Incident": "044498623",
    "USER_NIBRSClass": "23G",
    "USER_NIBRSDescription": "Theft of motor vehicle parts or accessory",
    "USER_District": "22",
    "USER_Beat": "22B40",
    "USER_Premise": "Parking Lot, Garage",
    "USER_OffenseAddressMiddle": "15549 JOHN F KENNEDY",
    "USER_BlockRange": "15500-15599",
    "USER_StreetName": "JOHN F KENNEDY",
    "USER_StreetType": "BLVD",
    "USER_Suffix": "",
    "USER_ZIPCode": "77032",
    "USER_ORI": "TXHPD0000",
    "DISTRICT_1": "B",
    "SNBNAME": "IAH / AIRPORT AREA",
    "OLC": "76X6WMV9+F7"
   }
  },
  {
   "attributes": {
    "OBJECTID": 8718235,
    "USER_RMSOccurrenceDate": 1679616000000,
    "USER_RMSOccurrenceHour": "11",
    "USER_Incident": "041785023",
    "USER_NIBRSClass": "23G",
    "USER_NIBRSDescription": "Theft of motor vehicle parts or accessory",
    "USER_District": "02",
    "USER_Beat": "02A40",
    "USER_Premise": "Residence, Home (Includes Apartment)",
    "USER_OffenseAddressMiddle": "2849 WASHINGTON",
    "USER_BlockRange": "2800-2899",
    "USER_StreetName": "WASHINGTON",
    "USER_StreetType": "AVE",
    "USER_Suffix": "",
    "USER_ZIPCode": "77007",
    "USER_ORI": "TXHPD0000",
    "DISTRICT_1": "",
    "SNBNAME": "",
    "OLC": "86263349+HW"
   }
  },
  {
   "attributes": {
    "OBJECTID": 8718273,
    "USER_RMSOccurrenceDate": 1679616000000,
    "USER_RMSOccurrenceHour": "01",
    "USER_Incident": "041524623",
    "USER_NIBRSClass": "120",
    "USER_NIBRSDescription": "Robbery",
    "USER_District": "01",
    "USER_Beat": "01A10",
    "USER_Premise": "Airplane, Bus,Train Terminal",
    "USER_OffenseAddressMiddle": "1949 MAIN",
    "USER_BlockRange": "1900-1999",
    "USER_StreetName": "MAIN",
    "USER_StreetType": "ST",
    "USER_Suffix": "",
    "USER_ZIPCode": "77002",
    "USER_ORI": "TXHPD0000",
    "DISTRICT_1": "",
    "SNBNAME": "",
    "OLC": "8626334H+QV"
   }
  },
  {
   "attributes": {
    "OBJECTID": 8718224,
    "USER_RMSOccurrenceDate": 1679616000000,
    "USER_RMSOccurrenceHour": "02",
    "USER_Incident": "041530323",
    "USER_NIBRSClass": "220",
    "USER_NIBRSDescription": "Burglary, Breaking and Entering",
    "USER_District": "02",
    "USER_Beat": "02A40",
    "USER_Premise": "Bar, Nightclub",
    "USER_OffenseAddressMiddle": "1949 WASHINGTON",
    "USER_BlockRange": "1900-1999",
    "USER_StreetName": "WASHINGTON",
    "USER_StreetType": "AVE",
    "USER_Suffix": "",
    "USER_ZIPCode": "77007",
    "USER_ORI": "TXHPD0000",
    "DISTRICT_1": "",
    "SNBNAME": "",
    "OLC": "8626333H+W9"
   }
  },
  {
   "attributes": {
    "OBJECTID": 8718329,
    "USER_RMSOccurrenceDate": 1679616000000,
    "USER_RMSOccurrenceHour": "11",
    "USER_Incident": "041696223",
    "USER_NIBRSClass": "26A",
    "USER_NIBRSDescription": "False pretenses, swindle",
    "USER_District": "22",
    "USER_Beat": "22B40",
    "USER_Premise": "Other, Unknown",
    "USER_OffenseAddressMiddle": "8849 FM 1960",
    "USER_BlockRange": "8800-8899",
    "USER_StreetName": "FM 1960",
    "USER_StreetType": "BYP",
    "USER_Suffix": "W",
    "USER_ZIPCode": "77338",
    "USER_ORI": "TXHPD0000",
    "DISTRICT_1": "",
    "SNBNAME": "",
    "OLC": "86262XWM+FC"
   }
  },
  {
   "attributes": {
    "OBJECTID": 8718464,
    "USER_RMSOccurrenceDate": 1679616000000,
    "USER_RMSOccurrenceHour": "23",
    "USER_Incident": "042267623",
    "USER_NIBRSClass": "23F",
    "USER_NIBRSDescription": "Theft from motor vehicle",
    "USER_District": "18",
    "USER_Beat": "18F30",
    "USER_Premise": "Parking Lot, Garage",
    "USER_OffenseAddressMiddle": "2649 FOUNTAIN VIEW",
    "USER_BlockRange": "2600-2699",
    "USER_StreetName": "FOUNTAIN VIEW",
    "USER_StreetType": "DR",
    "USER_Suffix": "",
    "USER_ZIPCode": "77057",
    "USER_ORI": "TXHPD0000",
    "DISTRICT_1": "",
    "SNBNAME": "",
    "OLC": "86265RFR+WP"
   }
  },
  {
   "attributes": {
    "OBJECTID": 8718380,
    "USER_RMSOccurrenceDate": 1679616000000,
    "USER_RMSOccurrenceHour": "22",
    "USER_Incident": "042007523",
    "USER_NIBRSClass": "290",
    "USER_NIBRSDescription": "Destruction, damage, vandalism",
    "USER_District": "24",
    "USER_Beat": "24C50",
    "USER_Premise": "Parking Lot, Garage",
    "USER_OffenseAddressMiddle": "349 NORTHPARK",
    "USER_BlockRange": "300-399",
    "USER_StreetName": "NORTHPARK",
    "USER_StreetType": "DR",
    "USER_Suffix": "",
    "USER_ZIPCode": "77339",
    "USER_ORI": "TXHPD0000",
    "DISTRICT_1": "E",
    "SNBNAME": "KINGWOOD AREA",
    "OLC": "86263Q94+JH"
   }
  },
  {
   "attributes": {
    "OBJECTID": 8718334,
    "USER_RMSOccurrenceDate": 1679616000000,
    "USER_RMSOccurrenceHour": "08",
    "USER_Incident": "055119923",
    "USER_NIBRSClass": "26F",
    "USER_NIBRSDescription": "Identify theft",
    "USER_District": "24",
    "USER_Beat": "24C20",
    "USER_Premise": "Airplane, Bus,Train Terminal",
    "USER_OffenseAddressMiddle": "3849 WILDWOOD RIDGE",
    "USER_BlockRange": "3800-3899",
    "USER_StreetName": "WILDWOOD RIDGE",
    "USER_StreetType": "DR",
    "USER_Suffix": "",
    "USER_ZIPCode": "77339",
    "USER_ORI": "TXHPD0000",
    "DISTRICT_1": "E",
    "SNBNAME": "KINGWOOD AREA",
    "OLC": "86263R35+2R"
   }
  }
 ]
}